ssp_api/__init__.py
ssp_api/account.py
ssp_api/account_id.py
ssp_api/account_management.py
ssp_api/accounts.py
ssp_api/blacklist_id.py
ssp_api/blacklists.py
ssp_api/categories.py
ssp_api/category_id.py
ssp_api/client.py
ssp_api/connection.py
ssp_api/items.py
ssp_api/network.py
ssp_api/network_id.py
ssp_api/networks.py
ssp_api/provisioning.py
ssp_api/records.py
ssp_api/sponsor.py
ssp_api/sponsor_id.py
ssp_api/sponsors.py
ssp_api/subnet_id.py
ssp_api/subnets.py
ssp_api/user_id.py
ssp_api/users.py
ssp_api/vip_id.py
ssp_api/vips.py
ssp_api/whitelist_id.py
ssp_api/whitelists.py
ssp_sdk_python-0.22.dist-info/DESCRIPTION.rst
ssp_sdk_python-0.22.dist-info/METADATA
ssp_sdk_python-0.22.dist-info/RECORD
ssp_sdk_python-0.22.dist-info/WHEEL
ssp_sdk_python-0.22.dist-info/metadata.json
ssp_sdk_python-0.22.dist-info/top_level.txt
