Metadata-Version: 2.0
Name: ssp-sdk-python
Version: 0.22
Summary: A Python client for communicating with Neustars Security Services Platform
Home-page: https://github.com/ultradns/ssp-sdk-python
Author: Shane Barbetta
Author-email: shane@barbetta.me
License: Apache License, Version 2.0
Keywords: ssp_api
Platform: UNKNOWN
Classifier: Development Status :: 5 - Production/Stable
Classifier: Topic :: Utilities
Classifier: License :: OSI Approved :: Apache Software License
Requires-Dist: requests
